mpgkit/__init__.py
mpgkit/cli.py
mpgkit/keymanager.py
mpgkit-1.0.3.dist-info/licenses/LICENSE
mpgkit-1.0.3.dist-info/METADATA
mpgkit-1.0.3.dist-info/WHEEL
mpgkit-1.0.3.dist-info/entry_points.txt
mpgkit-1.0.3.dist-info/top_level.txt
mpgkit-1.0.3.dist-info/RECORD
