Metadata-Version: 2.4
Name: mpgkit
Version: 1.0.3
Summary: mPGkit - Matel's PGP toolkit
Author: Matel
Requires-Python: >=3.8
License-File: LICENSE
Requires-Dist: python-gnupg
Dynamic: author
Dynamic: description
Dynamic: description-content-type
Dynamic: license-file
Dynamic: requires-dist
Dynamic: requires-python
Dynamic: summary
